barktools/__init__.py
barktools/base_utils.py
barktools/compute_utils.py
barktools/plot_utils.py
barktools/ssh_utils.py
scripts/__init__.py
scripts/index_files.py
barktools-0.0.2.dist-info/METADATA
barktools-0.0.2.dist-info/WHEEL
barktools-0.0.2.dist-info/entry_points.txt
barktools-0.0.2.dist-info/top_level.txt
barktools-0.0.2.dist-info/RECORD
