Metadata-Version: 2.1
Name: barktools
Version: 0.0.2
Summary: Package containing various useful python modules and scripts
Home-page: https://github.com/BarkenBark/python-tools
Author: Oscar Bark
Author-email: kurshid.ognianov@protonmail.com
Classifier: Programming Language :: Python :: 3
Classifier: License :: OSI Approved :: MIT License
Classifier: Operating System :: OS Independent
Requires-Python: >=3.6
